README.md
setup.py
aroundtheworlds/aroundtheworlds.py
aroundtheworlds.egg-info/PKG-INFO
aroundtheworlds.egg-info/SOURCES.txt
aroundtheworlds.egg-info/dependency_links.txt
aroundtheworlds.egg-info/entry_points.txt
aroundtheworlds.egg-info/requires.txt
aroundtheworlds.egg-info/top_level.txt