Metadata-Version: 1.1
Name: aroundtheworlds
Version: 0.0.1.dev1
Summary: Around the worlds in 80 days.
Home-page: https://github.com/illume/aroundtheworlds
Author: Rene Dudfield
Author-email: renesd@gmail.com
License: LGPL
Platform: UNKNOWN
Classifier: Development Status :: 1 - Planning
Classifier: Programming Language :: Python :: 3
Classifier: Programming Language :: Python :: 3.6
Classifier: Topic :: Software Development :: Libraries :: pygame
Classifier: Topic :: Games/Entertainment :: Arcade
